muaompc/__init__.py
muaompc/ldt.py
muaompc/version.py
muaompc/_ldt/__init__.py
muaompc/_ldt/codegen/__init__.py
muaompc/_ldt/codegen/codegen.py
muaompc/_ldt/codegen/common/__init__.py
muaompc/_ldt/codegen/common/codegen.py
muaompc/_ldt/codegen/common/codegenmat.py
muaompc/_ldt/codegen/common/tmpl/Makefile.long
muaompc/_ldt/codegen/common/tmpl/cjson.c
muaompc/_ldt/codegen/common/tmpl/tmpl_Makefile.mk
muaompc/_ldt/codegen/common/tmpl/tmpl_arithmetic.h
muaompc/_ldt/codegen/common/tmpl/tmpl_dynmem.c
muaompc/_ldt/codegen/common/tmpl/tmpl_dynmem.h
muaompc/_ldt/codegen/common/tmpl/tmpl_fipops.c
muaompc/_ldt/codegen/common/tmpl/tmpl_fipops.h
muaompc/_ldt/codegen/common/tmpl/tmpl_mtxops.c
muaompc/_ldt/codegen/common/tmpl/tmpl_mtxops.h
muaompc/_ldt/codegen/common/tmpl/include/cjson.h
muaompc/_ldt/codegen/common/tmpl/include/mc04types.h
muaompc/_ldt/codegen/common/tmpl/include/mpcstdint.h
muaompc/_ldt/codegen/common/tmpl/matlab/.matlab.c.swp
muaompc/_ldt/codegen/common/tmpl/matlab/tmpl_matlab.c
muaompc/_ldt/codegen/common/tmpl/matlab/tmpl_matlab.h
muaompc/_ldt/codegen/former/__init__.py
muaompc/_ldt/codegen/former/cvp/__init__.py
muaompc/_ldt/codegen/former/cvp/codegen.py
muaompc/_ldt/codegen/former/cvp/codegency.py
muaompc/_ldt/codegen/former/cvp/codegenmat.py
muaompc/_ldt/codegen/former/cvp/cvp.py
muaompc/_ldt/codegen/former/cvp/tmpl/tmpl_cvp.c
muaompc/_ldt/codegen/former/cvp/tmpl/tmpl_cvp.h
muaompc/_ldt/codegen/former/cvp/tmpl/tmpl_cvpdata.c
muaompc/_ldt/codegen/former/cvp/tmpl/tmpl_cvpdata.h
muaompc/_ldt/codegen/former/cvp/tmpl/tmpl_cvpdynmem.c
muaompc/_ldt/codegen/former/cvp/tmpl/tmpl_cvpdynmem.h
muaompc/_ldt/codegen/former/cvp/tmpl/cython/tmpl_Ccvp.pxd
muaompc/_ldt/codegen/former/cvp/tmpl/cython/tmpl_Ccvp.pxi
muaompc/_ldt/codegen/former/cvp/tmpl/cython/tmpl_Ccvp.pyx
muaompc/_ldt/codegen/former/cvp/tmpl/cython/tmpl_cvp.pyx
muaompc/_ldt/codegen/former/cvp/tmpl/cython/tmpl_cvpsetup.py
muaompc/_ldt/codegen/former/cvp/tmpl/matlab/tmpl_cvpmatlab.c
muaompc-1.0.0b1.dist-info/LICENSE
muaompc-1.0.0b1.dist-info/METADATA
muaompc-1.0.0b1.dist-info/WHEEL
muaompc-1.0.0b1.dist-info/top_level.txt
muaompc-1.0.0b1.dist-info/RECORD
