Metadata-Version: 2.1
Name: muaompc
Version: 1.0.0b1
Summary: muAO-MPC: microcontroller applications online model predictive control.
Home-page: https://github.com/muaompc/muaompc
Author: Pablo Zometa, et.al.
Author-email: zometa@anixet.com
Maintainer: Pablo Zometa
Maintainer-email: zometa@anixet.com
License: BSD
Platform: Windows
Platform: Linux
Platform: Mac OS-X
Classifier: Development Status :: 4 - Beta
Classifier: Intended Audience :: Science/Research
Classifier: Intended Audience :: Developers
Classifier: License :: OSI Approved :: BSD License
Classifier: Programming Language :: C
Classifier: Programming Language :: Python
Classifier: Programming Language :: Python :: 3
Classifier: Topic :: Scientific/Engineering
Classifier: Operating System :: OS Independent
License-File: LICENSE
Requires-Dist: cython
Requires-Dist: numpy
Requires-Dist: scipy
Requires-Dist: pyparsing
